{
  "data": [
    {
      "assists": 679,
      "evGoals": 268,
      "evPoints": 633,
      "faceoffWinPct": 0.45369,
      "gameWinningGoals": 45,
      "gamesPlayed": 1330,
      "goals": 385,
      "lastName": "Whitney",
      "otGoals": 6,
      "penaltyMinutes": 465,
      "playerId": 8458537,
      "plusMinus": -79,
      "points": 1064,
      "pointsPerGame": 0.8,
      "positionCode": "L",
      "ppGoals": 112,
      "ppPoints": 423,
      "shGoals": 5,
      "shPoints": 8,
      "shootingPct": 0.12664,
      "shootsCatches": "R",
      "shots": 3040,
      "skaterFullName": "Ray Whitney",
      "timeOnIcePerGame": null
    },
    {
      "assists": 599,
      "evGoals": 288,
      "evPoints": 631,
      "faceoffWinPct": 0.44301,
      "gameWinningGoals": 70,
      "gamesPlayed": 1316,
      "goals": 430,
      "lastName": "Kovalev",
      "otGoals": 8,
      "penaltyMinutes": 1304,
      "playerId": 8458529,
      "plusMinus": -31,
      "points": 1029,
      "pointsPerGame": 0.78191,
      "positionCode": "R",
      "ppGoals": 133,
      "ppPoints": 380,
      "shGoals": 9,
      "shPoints": 18,
      "shootingPct": 0.11994,
      "shootsCatches": "L",
      "shots": 3585,
      "skaterFullName": "Alex Kovalev",
      "timeOnIcePerGame": null
    },
    {
      "assists": 636,
      "evGoals": 162,
      "evPoints": 530,
      "faceoffWinPct": 0.48364,
      "gameWinningGoals": 43,
      "gamesPlayed": 708,
      "goals": 249,
      "lastName": "Forsberg",
      "otGoals": 4,
      "penaltyMinutes": 690,
      "playerId": 8458520,
      "plusMinus": 238,
      "points": 885,
      "pointsPerGame": 1.25,
      "positionCode": "C",
      "ppGoals": 71,
      "ppPoints": 323,
      "shGoals": 16,
      "shPoints": 32,
      "shootingPct": 0.14707,
      "shootsCatches": "L",
      "shots": 1693,
      "skaterFullName": "Peter Forsberg",
      "timeOnIcePerGame": null
    },
    {
      "assists": 474,
      "evGoals": 263,
      "evPoints": 533,
      "faceoffWinPct": 0.38554,
      "gameWinningGoals": 53,
      "gamesPlayed": 1117,
      "goals": 395,
      "lastName": "Naslund",
      "otGoals": 5,
      "penaltyMinutes": 736,
      "playerId": 8458530,
      "plusMinus": 6,
      "points": 869,
      "pointsPerGame": 0.77797,
      "positionCode": "L",
      "ppGoals": 126,
      "ppPoints": 328,
      "shGoals": 6,
      "shPoints": 8,
      "shootingPct": 0.12967,
      "shootsCatches": "L",
      "shots": 3046,
      "skaterFullName": "Markus Naslund",
      "timeOnIcePerGame": null
    },
    {
      "assists": 493,
      "evGoals": 254,
      "evPoints": 593,
      "faceoffWinPct": 0.56834,
      "gameWinningGoals": 46,
      "gamesPlayed": 760,
      "goals": 372,
      "lastName": "Lindros",
      "otGoals": 6,
      "penaltyMinutes": 1398,
      "playerId": 8458515,
      "plusMinus": 215,
      "points": 865,
      "pointsPerGame": 1.13815,
      "positionCode": "C",
      "ppGoals": 111,
      "ppPoints": 263,
      "shGoals": 7,
      "shPoints": 9,
      "shootingPct": 0.16089,
      "shootsCatches": "R",
      "shots": 2312,
      "skaterFullName": "Eric Lindros",
      "timeOnIcePerGame": null
    },
    {
      "assists": 419,
      "evGoals": 211,
      "evPoints": 458,
      "faceoffWinPct": 0.46869,
      "gameWinningGoals": 72,
      "gamesPlayed": 1256,
      "goals": 342,
      "lastName": "Rolston",
      "otGoals": 6,
      "penaltyMinutes": 472,
      "playerId": 8458525,
      "plusMinus": 65,
      "points": 761,
      "pointsPerGame": 0.60589,
      "positionCode": "R",
      "ppGoals": 98,
      "ppPoints": 260,
      "shGoals": 33,
      "shPoints": 43,
      "shootingPct": 0.08915,
      "shootsCatches": "L",
      "shots": 3836,
      "skaterFullName": "Brian Rolston",
      "timeOnIcePerGame": null
    },
    {
      "assists": 568,
      "evGoals": 81,
      "evPoints": 388,
      "faceoffWinPct": 0.23076,
      "gameWinningGoals": 39,
      "gamesPlayed": 1263,
      "goals": 172,
      "lastName": "Niedermayer",
      "otGoals": 13,
      "penaltyMinutes": 784,
      "playerId": 8458517,
      "plusMinus": 167,
      "points": 740,
      "pointsPerGame": 0.5859,
      "positionCode": "D",
      "ppGoals": 90,
      "ppPoints": 335,
      "shGoals": 1,
      "shPoints": 17,
      "shootingPct": 0.0706,
      "shootsCatches": "L",
      "shots": 2436,
      "skaterFullName": "Scott Niedermayer",
      "timeOnIcePerGame": null
    },
    {
      "assists": 384,
      "evGoals": 218,
      "evPoints": 431,
      "faceoffWinPct": 0.4054,
      "gameWinningGoals": 45,
      "gamesPlayed": 684,
      "goals": 329,
      "lastName": "Palffy",
      "otGoals": 5,
      "penaltyMinutes": 322,
      "playerId": 8458540,
      "plusMinus": 83,
      "points": 713,
      "pointsPerGame": 1.04239,
      "positionCode": "R",
      "ppGoals": 92,
      "ppPoints": 256,
      "shGoals": 19,
      "shPoints": 26,
      "shootingPct": 0.15402,
      "shootsCatches": "L",
      "shots": 2136,
      "skaterFullName": "Ziggy Palffy",
      "timeOnIcePerGame": null
    },
    {
      "assists": 470,
      "evGoals": 146,
      "evPoints": 476,
      "faceoffWinPct": 0.47734,
      "gameWinningGoals": 33,
      "gamesPlayed": 920,
      "goals": 209,
      "lastName": "Nylander",
      "otGoals": 5,
      "penaltyMinutes": 468,
      "playerId": 8458573,
      "plusMinus": 75,
      "points": 679,
      "pointsPerGame": 0.73804,
      "positionCode": "C",
      "ppGoals": 63,
      "ppPoints": 201,
      "shGoals": 0,
      "shPoints": 2,
      "shootingPct": 0.12507,
      "shootsCatches": "L",
      "shots": 1671,
      "skaterFullName": "Michael Nylander",
      "timeOnIcePerGame": null
    },
    {
      "assists": 481,
      "evGoals": 140,
      "evPoints": 473,
      "faceoffWinPct": 0.51478,
      "gameWinningGoals": 33,
      "gamesPlayed": 957,
      "goals": 196,
      "lastName": "Stumpel",
      "otGoals": 4,
      "penaltyMinutes": 245,
      "playerId": 8458554,
      "plusMinus": 47,
      "points": 677,
      "pointsPerGame": 0.70741,
      "positionCode": "L",
      "ppGoals": 53,
      "ppPoints": 194,
      "shGoals": 3,
      "shPoints": 10,
      "shootingPct": 0.12588,
      "shootsCatches": "R",
      "shots": 1557,
      "skaterFullName": "Jozef Stumpel",
      "timeOnIcePerGame": null
    },
    {
      "assists": 314,
      "evGoals": 242,
      "evPoints": 481,
      "faceoffWinPct": 0.37558,
      "gameWinningGoals": 55,
      "gamesPlayed": 1009,
      "goals": 337,
      "lastName": "Murray",
      "otGoals": 11,
      "penaltyMinutes": 679,
      "playerId": 8458532,
      "plusMinus": 14,
      "points": 651,
      "pointsPerGame": 0.64519,
      "positionCode": "R",
      "ppGoals": 86,
      "ppPoints": 155,
      "shGoals": 9,
      "shPoints": 15,
      "shootingPct": 0.13082,
      "shootsCatches": "R",
      "shots": 2576,
      "skaterFullName": "Glen Murray",
      "timeOnIcePerGame": null
    },
    {
      "assists": 371,
      "evGoals": 165,
      "evPoints": 412,
      "faceoffWinPct": 0.42937,
      "gameWinningGoals": 35,
      "gamesPlayed": 961,
      "goals": 241,
      "lastName": "Rucinsky",
      "otGoals": 2,
      "penaltyMinutes": 821,
      "playerId": 8458534,
      "plusMinus": 46,
      "points": 612,
      "pointsPerGame": 0.63683,
      "positionCode": "L",
      "ppGoals": 61,
      "ppPoints": 178,
      "shGoals": 15,
      "shPoints": 22,
      "shootingPct": 0.11167,
      "shootsCatches": "L",
      "shots": 2158,
      "skaterFullName": "Martin Rucinsky",
      "timeOnIcePerGame": null
    },
    {
      "assists": 397,
      "evGoals": 96,
      "evPoints": 286,
      "faceoffWinPct": null,
      "gameWinningGoals": 26,
      "gamesPlayed": 875,
      "goals": 167,
      "lastName": "Ozolinsh",
      "otGoals": 3,
      "penaltyMinutes": 638,
      "playerId": 8458544,
      "plusMinus": -44,
      "points": 564,
      "pointsPerGame": 0.64457,
      "positionCode": "D",
      "ppGoals": 67,
      "ppPoints": 271,
      "shGoals": 4,
      "shPoints": 7,
      "shootingPct": 0.09429,
      "shootsCatches": "L",
      "shots": 1771,
      "skaterFullName": "Sandis Ozolinsh",
      "timeOnIcePerGame": null
    },
    {
      "assists": 270,
      "evGoals": 192,
      "evPoints": 377,
      "faceoffWinPct": 0.352,
      "gameWinningGoals": 36,
      "gamesPlayed": 1068,
      "goals": 278,
      "lastName": "Knuble",
      "otGoals": 4,
      "penaltyMinutes": 641,
      "playerId": 8458590,
      "plusMinus": 76,
      "points": 548,
      "pointsPerGame": 0.5131,
      "positionCode": "R",
      "ppGoals": 81,
      "ppPoints": 164,
      "shGoals": 5,
      "shPoints": 7,
      "shootingPct": 0.13872,
      "shootsCatches": "R",
      "shots": 2004,
      "skaterFullName": "Mike Knuble",
      "timeOnIcePerGame": null
    },
    {
      "assists": 269,
      "evGoals": 175,
      "evPoints": 351,
      "faceoffWinPct": 0.61137,
      "gameWinningGoals": 41,
      "gamesPlayed": 859,
      "goals": 247,
      "lastName": "Perreault",
      "otGoals": 5,
      "penaltyMinutes": 402,
      "playerId": 8458561,
      "plusMinus": -20,
      "points": 516,
      "pointsPerGame": 0.60069,
      "positionCode": "C",
      "ppGoals": 63,
      "ppPoints": 151,
      "shGoals": 9,
      "shPoints": 14,
      "shootingPct": 0.14719,
      "shootsCatches": "L",
      "shots": 1678,
      "skaterFullName": "Yanic Perreault",
      "timeOnIcePerGame": null
    },
    {
      "assists": 375,
      "evGoals": 44,
      "evPoints": 225,
      "faceoffWinPct": 0.33333,
      "gameWinningGoals": 13,
      "gamesPlayed": 1085,
      "goals": 96,
      "lastName": "Zhitnik",
      "otGoals": 2,
      "penaltyMinutes": 1268,
      "playerId": 8458595,
      "plusMinus": -53,
      "points": 471,
      "pointsPerGame": 0.4341,
      "positionCode": "D",
      "ppGoals": 47,
      "ppPoints": 229,
      "shGoals": 5,
      "shPoints": 17,
      "shootingPct": 0.04387,
      "shootsCatches": "L",
      "shots": 2188,
      "skaterFullName": "Alexei Zhitnik",
      "timeOnIcePerGame": null
    },
    {
      "assists": 262,
      "evGoals": 138,
      "evPoints": 331,
      "faceoffWinPct": 0.45714,
      "gameWinningGoals": 29,
      "gamesPlayed": 996,
      "goals": 186,
      "lastName": "McAmmond",
      "otGoals": 2,
      "penaltyMinutes": 490,
      "playerId": 8458536,
      "plusMinus": 36,
      "points": 448,
      "pointsPerGame": 0.44979,
      "positionCode": "C",
      "ppGoals": 40,
      "ppPoints": 103,
      "shGoals": 8,
      "shPoints": 14,
      "shootingPct": 0.12567,
      "shootsCatches": "L",
      "shots": 1480,
      "skaterFullName": "Dean McAmmond",
      "timeOnIcePerGame": null
    },
    {
      "assists": 220,
      "evGoals": 156,
      "evPoints": 304,
      "faceoffWinPct": 0.21212,
      "gameWinningGoals": 20,
      "gamesPlayed": 745,
      "goals": 215,
      "lastName": "Czerkawski",
      "otGoals": 3,
      "penaltyMinutes": 274,
      "playerId": 8458620,
      "plusMinus": -54,
      "points": 435,
      "pointsPerGame": 0.58389,
      "positionCode": "R",
      "ppGoals": 58,
      "ppPoints": 129,
      "shGoals": 1,
      "shPoints": 2,
      "shootingPct": 0.11684,
      "shootsCatches": "R",
      "shots": 1840,
      "skaterFullName": "Mariusz Czerkawski",
      "timeOnIcePerGame": null
    },
    {
      "assists": 225,
      "evGoals": 129,
      "evPoints": 310,
      "faceoffWinPct": 0.49128,
      "gameWinningGoals": 26,
      "gamesPlayed": 790,
      "goals": 171,
      "lastName": "Konowalchuk",
      "otGoals": 5,
      "penaltyMinutes": 703,
      "playerId": 8458572,
      "plusMinus": 69,
      "points": 396,
      "pointsPerGame": 0.50126,
      "positionCode": "L",
      "ppGoals": 34,
      "ppPoints": 71,
      "shGoals": 8,
      "shPoints": 15,
      "shootingPct": 0.12025,
      "shootsCatches": "L",
      "shots": 1422,
      "skaterFullName": "Steve Konowalchuk",
      "timeOnIcePerGame": null
    },
    {
      "assists": 200,
      "evGoals": 118,
      "evPoints": 274,
      "faceoffWinPct": 0.52762,
      "gameWinningGoals": 29,
      "gamesPlayed": 991,
      "goals": 181,
      "lastName": "Lapointe",
      "otGoals": 1,
      "penaltyMinutes": 1417,
      "playerId": 8458524,
      "plusMinus": -40,
      "points": 381,
      "pointsPerGame": 0.38446,
      "positionCode": "R",
      "ppGoals": 59,
      "ppPoints": 102,
      "shGoals": 4,
      "shPoints": 5,
      "shootingPct": 0.11159,
      "shootsCatches": "R",
      "shots": 1622,
      "skaterFullName": "Martin Lapointe",
      "timeOnIcePerGame": null
    },
    {
      "assists": 167,
      "evGoals": 132,
      "evPoints": 261,
      "faceoffWinPct": 0.44247,
      "gameWinningGoals": 31,
      "gamesPlayed": 674,
      "goals": 192,
      "lastName": "Savage",
      "otGoals": 4,
      "penaltyMinutes": 321,
      "playerId": 8458682,
      "plusMinus": -80,
      "points": 359,
      "pointsPerGame": 0.53264,
      "positionCode": "L",
      "ppGoals": 58,
      "ppPoints": 96,
      "shGoals": 2,
      "shPoints": 2,
      "shootingPct": 0.1325,
      "shootsCatches": "L",
      "shots": 1449,
      "skaterFullName": "Brian Savage",
      "timeOnIcePerGame": null
    },
    {
      "assists": 179,
      "evGoals": 103,
      "evPoints": 223,
      "faceoffWinPct": 0.55319,
      "gameWinningGoals": 14,
      "gamesPlayed": 575,
      "goals": 143,
      "lastName": "Falloon",
      "otGoals": 0,
      "penaltyMinutes": 141,
      "playerId": 8458516,
      "plusMinus": -66,
      "points": 322,
      "pointsPerGame": 0.56,
      "positionCode": "R",
      "ppGoals": 39,
      "ppPoints": 95,
      "shGoals": 1,
      "shPoints": 4,
      "shootingPct": 0.11259,
      "shootsCatches": "R",
      "shots": 1270,
      "skaterFullName": "Pat Falloon",
      "timeOnIcePerGame": null
    },
    {
      "assists": 206,
      "evGoals": 50,
      "evPoints": 170,
      "faceoffWinPct": 0.33333,
      "gameWinningGoals": 17,
      "gamesPlayed": 748,
      "goals": 94,
      "lastName": "Boucher",
      "otGoals": 1,
      "penaltyMinutes": 702,
      "playerId": 8458527,
      "plusMinus": 57,
      "points": 300,
      "pointsPerGame": 0.40106,
      "positionCode": "D",
      "ppGoals": 42,
      "ppPoints": 123,
      "shGoals": 2,
      "shPoints": 7,
      "shootingPct": 0.05724,
      "shootsCatches": "R",
      "shots": 1642,
      "skaterFullName": "Philippe Boucher",
      "timeOnIcePerGame": null
    },
    {
      "assists": 210,
      "evGoals": 34,
      "evPoints": 132,
      "faceoffWinPct": null,
      "gameWinningGoals": 8,
      "gamesPlayed": 699,
      "goals": 64,
      "lastName": "Kravchuk",
      "otGoals": 0,
      "penaltyMinutes": 251,
      "playerId": 8458585,
      "plusMinus": -57,
      "points": 274,
      "pointsPerGame": 0.39198,
      "positionCode": "D",
      "ppGoals": 28,
      "ppPoints": 137,
      "shGoals": 2,
      "shPoints": 5,
      "shootingPct": 0.04306,
      "shootsCatches": "L",
      "shots": 1486,
      "skaterFullName": "Igor Kravchuk",
      "timeOnIcePerGame": null
    },
    {
      "assists": 206,
      "evGoals": 33,
      "evPoints": 139,
      "faceoffWinPct": 0.25,
      "gameWinningGoals": 7,
      "gamesPlayed": 556,
      "goals": 54,
      "lastName": "Mironov",
      "otGoals": 0,
      "penaltyMinutes": 568,
      "playerId": 8458672,
      "plusMinus": 29,
      "points": 260,
      "pointsPerGame": 0.46762,
      "positionCode": "D",
      "ppGoals": 20,
      "ppPoints": 115,
      "shGoals": 1,
      "shPoints": 6,
      "shootingPct": 0.05521,
      "shootsCatches": "R",
      "shots": 978,
      "skaterFullName": "Dmitri Mironov",
      "timeOnIcePerGame": null
    },
    {
      "assists": 145,
      "evGoals": 65,
      "evPoints": 170,
      "faceoffWinPct": 0.48125,
      "gameWinningGoals": 15,
      "gamesPlayed": 547,
      "goals": 93,
      "lastName": "Holzinger",
      "otGoals": 0,
      "penaltyMinutes": 339,
      "playerId": 8458638,
      "plusMinus": -62,
      "points": 238,
      "pointsPerGame": 0.4351,
      "positionCode": "C",
      "ppGoals": 21,
      "ppPoints": 55,
      "shGoals": 7,
      "shPoints": 13,
      "shootingPct": 0.11552,
      "shootsCatches": "R",
      "shots": 805,
      "skaterFullName": "Brian Holzinger",
      "timeOnIcePerGame": null
    },
    {
      "assists": 134,
      "evGoals": 82,
      "evPoints": 196,
      "faceoffWinPct": 0.28342,
      "gameWinningGoals": 16,
      "gamesPlayed": 634,
      "goals": 101,
      "lastName": "Poulin",
      "otGoals": 0,
      "penaltyMinutes": 299,
      "playerId": 8458523,
      "plusMinus": -30,
      "points": 235,
      "pointsPerGame": 0.37066,
      "positionCode": "L",
      "ppGoals": 13,
      "ppPoints": 28,
      "shGoals": 6,
      "shPoints": 11,
      "shootingPct": 0.11952,
      "shootsCatches": "L",
      "shots": 845,
      "skaterFullName": "Patrick Poulin",
      "timeOnIcePerGame": null
    },
    {
      "assists": 198,
      "evGoals": 26,
      "evPoints": 187,
      "faceoffWinPct": 0.45454,
      "gameWinningGoals": 9,
      "gamesPlayed": 1224,
      "goals": 31,
      "lastName": "O'Donnell",
      "otGoals": 4,
      "penaltyMinutes": 1809,
      "playerId": 8458637,
      "plusMinus": 87,
      "points": 229,
      "pointsPerGame": 0.18709,
      "positionCode": "D",
      "ppGoals": 4,
      "ppPoints": 25,
      "shGoals": 1,
      "shPoints": 17,
      "shootingPct": 0.0349,
      "shootsCatches": "L",
      "shots": 888,
      "skaterFullName": "Sean O'Donnell",
      "timeOnIcePerGame": null
    },
    {
      "assists": 182,
      "evGoals": 24,
      "evPoints": 165,
      "faceoffWinPct": 0.33333,
      "gameWinningGoals": 6,
      "gamesPlayed": 786,
      "goals": 43,
      "lastName": "Yushkevich",
      "otGoals": 1,
      "penaltyMinutes": 659,
      "playerId": 8458636,
      "plusMinus": -21,
      "points": 225,
      "pointsPerGame": 0.28625,
      "positionCode": "D",
      "ppGoals": 15,
      "ppPoints": 49,
      "shGoals": 4,
      "shPoints": 11,
      "shootingPct": 0.03839,
      "shootsCatches": "R",
      "shots": 1120,
      "skaterFullName": "Dmitry Yushkevich",
      "timeOnIcePerGame": null
    },
    {
      "assists": 141,
      "evGoals": 75,
      "evPoints": 204,
      "faceoffWinPct": 0.44244,
      "gameWinningGoals": 16,
      "gamesPlayed": 777,
      "goals": 83,
      "lastName": "Lindsay",
      "otGoals": 1,
      "penaltyMinutes": 922,
      "playerId": 8458617,
      "plusMinus": -27,
      "points": 224,
      "pointsPerGame": 0.28828,
      "positionCode": "L",
      "ppGoals": 0,
      "ppPoints": 3,
      "shGoals": 8,
      "shPoints": 17,
      "shootingPct": 0.07351,
      "shootsCatches": "L",
      "shots": 1129,
      "skaterFullName": "Bill Lindsay",
      "timeOnIcePerGame": null
    },
    {
      "assists": 164,
      "evGoals": 43,
      "evPoints": 173,
      "faceoffWinPct": 0.48275,
      "gameWinningGoals": 4,
      "gamesPlayed": 1001,
      "goals": 56,
      "lastName": "Staios",
      "otGoals": 1,
      "penaltyMinutes": 1322,
      "playerId": 8458541,
      "plusMinus": -86,
      "points": 220,
      "pointsPerGame": 0.21978,
      "positionCode": "D",
      "ppGoals": 9,
      "ppPoints": 38,
      "shGoals": 4,
      "shPoints": 9,
      "shootingPct": 0.04534,
      "shootsCatches": "R",
      "shots": 1235,
      "skaterFullName": "Steve Staios",
      "timeOnIcePerGame": null
    },
    {
      "assists": 115,
      "evGoals": 58,
      "evPoints": 149,
      "faceoffWinPct": 0.32142,
      "gameWinningGoals": 13,
      "gamesPlayed": 382,
      "goals": 72,
      "lastName": "Petrov",
      "otGoals": 2,
      "penaltyMinutes": 101,
      "playerId": 8458641,
      "plusMinus": -18,
      "points": 187,
      "pointsPerGame": 0.48952,
      "positionCode": "R",
      "ppGoals": 11,
      "ppPoints": 35,
      "shGoals": 3,
      "shPoints": 3,
      "shootingPct": 0.09903,
      "shootsCatches": "L",
      "shots": 727,
      "skaterFullName": "Oleg Petrov",
      "timeOnIcePerGame": null
    },
    {
      "assists": 139,
      "evGoals": 29,
      "evPoints": 136,
      "faceoffWinPct": 0.28571,
      "gameWinningGoals": 7,
      "gamesPlayed": 796,
      "goals": 39,
      "lastName": "Matvichuk",
      "otGoals": 3,
      "penaltyMinutes": 624,
      "playerId": 8458522,
      "plusMinus": 46,
      "points": 178,
      "pointsPerGame": 0.22361,
      "positionCode": "D",
      "ppGoals": 8,
      "ppPoints": 35,
      "shGoals": 2,
      "shPoints": 7,
      "shootingPct": 0.04681,
      "shootsCatches": "L",
      "shots": 833,
      "skaterFullName": "Richard Matvichuk",
      "timeOnIcePerGame": null
    },
    {
      "assists": 90,
      "evGoals": 62,
      "evPoints": 125,
      "faceoffWinPct": 0.38095,
      "gameWinningGoals": 10,
      "gamesPlayed": 366,
      "goals": 86,
      "lastName": "Dawe",
      "otGoals": 2,
      "penaltyMinutes": 162,
      "playerId": 8458549,
      "plusMinus": 8,
      "points": 176,
      "pointsPerGame": 0.48087,
      "positionCode": "R",
      "ppGoals": 20,
      "ppPoints": 46,
      "shGoals": 4,
      "shPoints": 5,
      "shootingPct": 0.1493,
      "shootsCatches": "L",
      "shots": 576,
      "skaterFullName": "Jason Dawe",
      "timeOnIcePerGame": null
    },
    {
      "assists": 88,
      "evGoals": 54,
      "evPoints": 109,
      "faceoffWinPct": 0.41295,
      "gameWinningGoals": 8,
      "gamesPlayed": 377,
      "goals": 81,
      "lastName": "Johansson",
      "otGoals": 0,
      "penaltyMinutes": 190,
      "playerId": 8458650,
      "plusMinus": -8,
      "points": 169,
      "pointsPerGame": 0.44827,
      "positionCode": "L",
      "ppGoals": 25,
      "ppPoints": 55,
      "shGoals": 2,
      "shPoints": 5,
      "shootingPct": 0.12347,
      "shootsCatches": "L",
      "shots": 656,
      "skaterFullName": "Andreas Johansson",
      "timeOnIcePerGame": null
    },
    {
      "assists": 135,
      "evGoals": 23,
      "evPoints": 133,
      "faceoffWinPct": 1,
      "gameWinningGoals": 4,
      "gamesPlayed": 739,
      "goals": 27,
      "lastName": "Ulanov",
      "otGoals": 0,
      "penaltyMinutes": 1151,
      "playerId": 8458715,
      "plusMinus": 13,
      "points": 162,
      "pointsPerGame": 0.21921,
      "positionCode": "D",
      "ppGoals": 4,
      "ppPoints": 20,
      "shGoals": 0,
      "shPoints": 9,
      "shootingPct": 0.05103,
      "shootsCatches": "L",
      "shots": 529,
      "skaterFullName": "Igor Ulanov",
      "timeOnIcePerGame": null
    },
    {
      "assists": 107,
      "evGoals": 41,
      "evPoints": 134,
      "faceoffWinPct": 0.5,
      "gameWinningGoals": 9,
      "gamesPlayed": 839,
      "goals": 44,
      "lastName": "Ward",
      "otGoals": 3,
      "penaltyMinutes": 736,
      "playerId": 8458519,
      "plusMinus": -41,
      "points": 151,
      "pointsPerGame": 0.17997,
      "positionCode": "D",
      "ppGoals": 2,
      "ppPoints": 9,
      "shGoals": 1,
      "shPoints": 8,
      "shootingPct": 0.0648,
      "shootsCatches": "R",
      "shots": 679,
      "skaterFullName": "Aaron Ward",
      "timeOnIcePerGame": null
    },
    {
      "assists": 70,
      "evGoals": 62,
      "evPoints": 123,
      "faceoffWinPct": 0.44068,
      "gameWinningGoals": 13,
      "gamesPlayed": 613,
      "goals": 79,
      "lastName": "Wright",
      "otGoals": 3,
      "penaltyMinutes": 854,
      "playerId": 8458526,
      "plusMinus": -115,
      "points": 149,
      "pointsPerGame": 0.24306,
      "positionCode": "C",
      "ppGoals": 14,
      "ppPoints": 23,
      "shGoals": 3,
      "shPoints": 3,
      "shootingPct": 0.11064,
      "shootsCatches": "R",
      "shots": 714,
      "skaterFullName": "Tyler Wright",
      "timeOnIcePerGame": null
    },
    {
      "assists": 76,
      "evGoals": 63,
      "evPoints": 131,
      "faceoffWinPct": 0.17948,
      "gameWinningGoals": 12,
      "gamesPlayed": 736,
      "goals": 72,
      "lastName": "McCarthy",
      "otGoals": 2,
      "penaltyMinutes": 1534,
      "playerId": 8458566,
      "plusMinus": -81,
      "points": 148,
      "pointsPerGame": 0.20108,
      "positionCode": "R",
      "ppGoals": 9,
      "ppPoints": 17,
      "shGoals": 0,
      "shPoints": 0,
      "shootingPct": 0.09125,
      "shootsCatches": "R",
      "shots": 789,
      "skaterFullName": "Sandy McCarthy",
      "timeOnIcePerGame": null
    },
    {
      "assists": 112,
      "evGoals": 23,
      "evPoints": 107,
      "faceoffWinPct": 0.5,
      "gameWinningGoals": 3,
      "gamesPlayed": 819,
      "goals": 31,
      "lastName": "Lachance",
      "otGoals": 0,
      "penaltyMinutes": 567,
      "playerId": 8458518,
      "plusMinus": -76,
      "points": 143,
      "pointsPerGame": 0.1746,
      "positionCode": "D",
      "ppGoals": 7,
      "ppPoints": 30,
      "shGoals": 1,
      "shPoints": 6,
      "shootingPct": 0.04366,
      "shootsCatches": "L",
      "shots": 710,
      "skaterFullName": "Scott Lachance",
      "timeOnIcePerGame": null
    },
    {
      "assists": 75,
      "evGoals": 41,
      "evPoints": 86,
      "faceoffWinPct": 0.35714,
      "gameWinningGoals": 13,
      "gamesPlayed": 285,
      "goals": 61,
      "lastName": "Campbell",
      "otGoals": 0,
      "penaltyMinutes": 268,
      "playerId": 8458542,
      "plusMinus": -11,
      "points": 136,
      "pointsPerGame": 0.47719,
      "positionCode": "R",
      "ppGoals": 20,
      "ppPoints": 48,
      "shGoals": 0,
      "shPoints": 2,
      "shootingPct": 0.11254,
      "shootsCatches": "R",
      "shots": 542,
      "skaterFullName": "Jim Campbell",
      "timeOnIcePerGame": null
    },
    {
      "assists": 74,
      "evGoals": 47,
      "evPoints": 102,
      "faceoffWinPct": 0.44745,
      "gameWinningGoals": 9,
      "gamesPlayed": 362,
      "goals": 58,
      "lastName": "Corbet",
      "otGoals": 0,
      "penaltyMinutes": 420,
      "playerId": 8458538,
      "plusMinus": 23,
      "points": 132,
      "pointsPerGame": 0.36464,
      "positionCode": "L",
      "ppGoals": 11,
      "ppPoints": 29,
      "shGoals": 0,
      "shPoints": 1,
      "shootingPct": 0.09369,
      "shootsCatches": "L",
      "shots": 619,
      "skaterFullName": "Rene Corbet",
      "timeOnIcePerGame": null
    },
    {
      "assists": 99,
      "evGoals": 13,
      "evPoints": 79,
      "faceoffWinPct": null,
      "gameWinningGoals": 3,
      "gamesPlayed": 407,
      "goals": 22,
      "lastName": "Laukkanen",
      "otGoals": 0,
      "penaltyMinutes": 335,
      "playerId": 8458805,
      "plusMinus": -3,
      "points": 121,
      "pointsPerGame": 0.29729,
      "positionCode": "D",
      "ppGoals": 9,
      "ppPoints": 37,
      "shGoals": 0,
      "shPoints": 5,
      "shootingPct": 0.04508,
      "shootsCatches": "L",
      "shots": 488,
      "skaterFullName": "Janne Laukkanen",
      "timeOnIcePerGame": null
    },
    {
      "assists": 85,
      "evGoals": 21,
      "evPoints": 94,
      "faceoffWinPct": 0.33333,
      "gameWinningGoals": 7,
      "gamesPlayed": 812,
      "goals": 26,
      "lastName": "Cullimore",
      "otGoals": 2,
      "penaltyMinutes": 704,
      "playerId": 8458543,
      "plusMinus": -45,
      "points": 111,
      "pointsPerGame": 0.13669,
      "positionCode": "D",
      "ppGoals": 3,
      "ppPoints": 13,
      "shGoals": 2,
      "shPoints": 4,
      "shootingPct": 0.04193,
      "shootsCatches": "L",
      "shots": 620,
      "skaterFullName": "Jassen Cullimore",
      "timeOnIcePerGame": null
    },
    {
      "assists": 62,
      "evGoals": 36,
      "evPoints": 79,
      "faceoffWinPct": null,
      "gameWinningGoals": 2,
      "gamesPlayed": 215,
      "goals": 42,
      "lastName": "Lomakin",
      "otGoals": 0,
      "penaltyMinutes": 92,
      "playerId": 8458652,
      "plusMinus": 5,
      "points": 104,
      "pointsPerGame": 0.48372,
      "positionCode": "L",
      "ppGoals": 6,
      "ppPoints": 24,
      "shGoals": 0,
      "shPoints": 1,
      "shootingPct": 0.13548,
      "shootsCatches": "L",
      "shots": 310,
      "skaterFullName": "Andrei Lomakin",
      "timeOnIcePerGame": null
    },
    {
      "assists": 76,
      "evGoals": 20,
      "evPoints": 90,
      "faceoffWinPct": 0.44365,
      "gameWinningGoals": 3,
      "gamesPlayed": 341,
      "goals": 26,
      "lastName": "Ylonen",
      "otGoals": 0,
      "penaltyMinutes": 90,
      "playerId": 8458605,
      "plusMinus": 8,
      "points": 102,
      "pointsPerGame": 0.29912,
      "positionCode": "C",
      "ppGoals": 2,
      "ppPoints": 3,
      "shGoals": 4,
      "shPoints": 9,
      "shootingPct": 0.0686,
      "shootsCatches": "L",
      "shots": 379,
      "skaterFullName": "Juha Ylonen",
      "timeOnIcePerGame": null
    },
    {
      "assists": 49,
      "evGoals": 21,
      "evPoints": 56,
      "faceoffWinPct": 0.5,
      "gameWinningGoals": 1,
      "gamesPlayed": 233,
      "goals": 49,
      "lastName": "Oliver",
      "otGoals": 0,
      "penaltyMinutes": 84,
      "playerId": 8458658,
      "plusMinus": -31,
      "points": 98,
      "pointsPerGame": 0.4206,
      "positionCode": "R",
      "ppGoals": 28,
      "ppPoints": 42,
      "shGoals": 0,
      "shPoints": 0,
      "shootingPct": 0.1596,
      "shootsCatches": "R",
      "shots": 307,
      "skaterFullName": "David Oliver",
      "timeOnIcePerGame": null
    },
    {
      "assists": 80,
      "evGoals": 13,
      "evPoints": 79,
      "faceoffWinPct": 0.5,
      "gameWinningGoals": 3,
      "gamesPlayed": 557,
      "goals": 18,
      "lastName": "Karpa",
      "otGoals": 0,
      "penaltyMinutes": 1374,
      "playerId": 8458582,
      "plusMinus": -19,
      "points": 98,
      "pointsPerGame": 0.17594,
      "positionCode": "D",
      "ppGoals": 4,
      "ppPoints": 15,
      "shGoals": 1,
      "shPoints": 4,
      "shootingPct": 0.03742,
      "shootsCatches": "R",
      "shots": 481,
      "skaterFullName": "Dave Karpa",
      "timeOnIcePerGame": null
    },
    {
      "assists": 54,
      "evGoals": 32,
      "evPoints": 84,
      "faceoffWinPct": 0.51825,
      "gameWinningGoals": 4,
      "gamesPlayed": 312,
      "goals": 34,
      "lastName": "Gardiner",
      "otGoals": 0,
      "penaltyMinutes": 263,
      "playerId": 8458645,
      "plusMinus": -10,
      "points": 88,
      "pointsPerGame": 0.28205,
      "positionCode": "R",
      "ppGoals": 1,
      "ppPoints": 2,
      "shGoals": 1,
      "shPoints": 2,
      "shootingPct": 0.09826,
      "shootsCatches": "R",
      "shots": 346,
      "skaterFullName": "Bruce Gardiner",
      "timeOnIcePerGame": null
    },
    {
      "assists": 41,
      "evGoals": 17,
      "evPoints": 44,
      "faceoffWinPct": 0.77777,
      "gameWinningGoals": 4,
      "gamesPlayed": 134,
      "goals": 28,
      "lastName": "Peake",
      "otGoals": 0,
      "penaltyMinutes": 105,
      "playerId": 8458528,
      "plusMinus": 3,
      "points": 69,
      "pointsPerGame": 0.51492,
      "positionCode": "C",
      "ppGoals": 11,
      "ppPoints": 25,
      "shGoals": 0,
      "shPoints": 0,
      "shootingPct": 0.1081,
      "shootsCatches": "R",
      "shots": 259,
      "skaterFullName": "Pat Peake",
      "timeOnIcePerGame": null
    },
    {
      "assists": 46,
      "evGoals": 13,
      "evPoints": 57,
      "faceoffWinPct": null,
      "gameWinningGoals": 0,
      "gamesPlayed": 521,
      "goals": 14,
      "lastName": "Pushor",
      "otGoals": 0,
      "penaltyMinutes": 648,
      "playerId": 8458546,
      "plusMinus": -52,
      "points": 60,
      "pointsPerGame": 0.11516,
      "positionCode": "D",
      "ppGoals": 0,
      "ppPoints": 0,
      "shGoals": 1,
      "shPoints": 3,
      "shootingPct": 0.03398,
      "shootsCatches": "R",
      "shots": 412,
      "skaterFullName": "Jamie Pushor",
      "timeOnIcePerGame": null
    },
    {
      "assists": 36,
      "evGoals": 20,
      "evPoints": 48,
      "faceoffWinPct": 0.48684,
      "gameWinningGoals": 4,
      "gamesPlayed": 260,
      "goals": 23,
      "lastName": "Pronger",
      "otGoals": 0,
      "penaltyMinutes": 159,
      "playerId": 8458565,
      "plusMinus": -40,
      "points": 59,
      "pointsPerGame": 0.22692,
      "positionCode": "C",
      "ppGoals": 3,
      "ppPoints": 10,
      "shGoals": 0,
      "shPoints": 1,
      "shootingPct": 0.09663,
      "shootsCatches": "L",
      "shots": 238,
      "skaterFullName": "Sean Pronger",
      "timeOnIcePerGame": null
    },
    {
      "assists": 35,
      "evGoals": 18,
      "evPoints": 50,
      "faceoffWinPct": 0.47576,
      "gameWinningGoals": 2,
      "gamesPlayed": 196,
      "goals": 21,
      "lastName": "Darby",
      "otGoals": 0,
      "penaltyMinutes": 32,
      "playerId": 8458557,
      "plusMinus": -38,
      "points": 56,
      "pointsPerGame": 0.28571,
      "positionCode": "C",
      "ppGoals": 0,
      "ppPoints": 3,
      "shGoals": 3,
      "shPoints": 3,
      "shootingPct": 0.1,
      "shootsCatches": "R",
      "shots": 210,
      "skaterFullName": "Craig Darby",
      "timeOnIcePerGame": null
    },
    {
      "assists": 36,
      "evGoals": 10,
      "evPoints": 42,
      "faceoffWinPct": 0,
      "gameWinningGoals": 2,
      "gamesPlayed": 145,
      "goals": 16,
      "lastName": "Kennedy",
      "otGoals": 1,
      "penaltyMinutes": 112,
      "playerId": 8458611,
      "plusMinus": -1,
      "points": 52,
      "pointsPerGame": 0.35862,
      "positionCode": "C",
      "ppGoals": 6,
      "ppPoints": 10,
      "shGoals": 0,
      "shPoints": 0,
      "shootingPct": 0.07111,
      "shootsCatches": "R",
      "shots": 225,
      "skaterFullName": "Mike Kennedy",
      "timeOnIcePerGame": null
    },
    {
      "assists": 20,
      "evGoals": 24,
      "evPoints": 41,
      "faceoffWinPct": 0.41694,
      "gameWinningGoals": 10,
      "gamesPlayed": 193,
      "goals": 28,
      "lastName": "Valicevic",
      "otGoals": 0,
      "penaltyMinutes": 61,
      "playerId": 8458628,
      "plusMinus": -13,
      "points": 48,
      "pointsPerGame": 0.2487,
      "positionCode": "R",
      "ppGoals": 3,
      "ppPoints": 4,
      "shGoals": 1,
      "shPoints": 3,
      "shootingPct": 0.12844,
      "shootsCatches": "R",
      "shots": 218,
      "skaterFullName": "Rob Valicevic",
      "timeOnIcePerGame": 783.1865
    },
    {
      "assists": 26,
      "evGoals": 13,
      "evPoints": 30,
      "faceoffWinPct": 0.5,
      "gameWinningGoals": 2,
      "gamesPlayed": 142,
      "goals": 18,
      "lastName": "Lawrence",
      "otGoals": 0,
      "penaltyMinutes": 115,
      "playerId": 8458632,
      "plusMinus": -30,
      "points": 44,
      "pointsPerGame": 0.30985,
      "positionCode": "R",
      "ppGoals": 5,
      "ppPoints": 14,
      "shGoals": 0,
      "shPoints": 0,
      "shootingPct": 0.10404,
      "shootsCatches": "R",
      "shots": 173,
      "skaterFullName": "Mark Lawrence",
      "timeOnIcePerGame": null
    },
    {
      "assists": 20,
      "evGoals": 12,
      "evPoints": 30,
      "faceoffWinPct": 0.48192,
      "gameWinningGoals": 3,
      "gamesPlayed": 187,
      "goals": 17,
      "lastName": "LaFayette",
      "otGoals": 0,
      "penaltyMinutes": 103,
      "playerId": 8458579,
      "plusMinus": -14,
      "points": 37,
      "pointsPerGame": 0.19786,
      "positionCode": "C",
      "ppGoals": 2,
      "ppPoints": 4,
      "shGoals": 3,
      "shPoints": 3,
      "shootingPct": 0.07555,
      "shootsCatches": "R",
      "shots": 225,
      "skaterFullName": "Nathan LaFayette",
      "timeOnIcePerGame": null
    },
    {
      "assists": 30,
      "evGoals": 6,
      "evPoints": 29,
      "faceoffWinPct": 0.37301,
      "gameWinningGoals": 1,
      "gamesPlayed": 110,
      "goals": 7,
      "lastName": "Vujtek",
      "otGoals": 0,
      "penaltyMinutes": 38,
      "playerId": 8458587,
      "plusMinus": -15,
      "points": 37,
      "pointsPerGame": 0.33636,
      "positionCode": "L",
      "ppGoals": 1,
      "ppPoints": 8,
      "shGoals": 0,
      "shPoints": 0,
      "shootingPct": 0.04242,
      "shootsCatches": "L",
      "shots": 165,
      "skaterFullName": "Vladimir Vujtek",
      "timeOnIcePerGame": null
    },
    {
      "assists": 15,
      "evGoals": 9,
      "evPoints": 16,
      "faceoffWinPct": 0,
      "gameWinningGoals": 2,
      "gamesPlayed": 71,
      "goals": 16,
      "lastName": "Fraser",
      "otGoals": 1,
      "penaltyMinutes": 24,
      "playerId": 8458705,
      "plusMinus": -7,
      "points": 31,
      "pointsPerGame": 0.43661,
      "positionCode": "R",
      "ppGoals": 7,
      "ppPoints": 15,
      "shGoals": 0,
      "shPoints": 0,
      "shootingPct": 0.15238,
      "shootsCatches": "R",
      "shots": 105,
      "skaterFullName": "Scott Fraser",
      "timeOnIcePerGame": null
    },
    {
      "assists": 22,
      "evGoals": 6,
      "evPoints": 24,
      "faceoffWinPct": 0.46485,
      "gameWinningGoals": 2,
      "gamesPlayed": 139,
      "goals": 8,
      "lastName": "Kesa",
      "otGoals": 0,
      "penaltyMinutes": 66,
      "playerId": 8458609,
      "plusMinus": -24,
      "points": 30,
      "pointsPerGame": 0.21582,
      "positionCode": "R",
      "ppGoals": 1,
      "ppPoints": 3,
      "shGoals": 1,
      "shPoints": 3,
      "shootingPct": 0.07547,
      "shootsCatches": "R",
      "shots": 106,
      "skaterFullName": "Dan Kesa",
      "timeOnIcePerGame": null
    },
    {
      "assists": 18,
      "evGoals": 6,
      "evPoints": 23,
      "faceoffWinPct": null,
      "gameWinningGoals": 2,
      "gamesPlayed": 98,
      "goals": 11,
      "lastName": "Craigwell",
      "otGoals": 0,
      "penaltyMinutes": 28,
      "playerId": 8458711,
      "plusMinus": -20,
      "points": 29,
      "pointsPerGame": 0.29591,
      "positionCode": "C",
      "ppGoals": 4,
      "ppPoints": 5,
      "shGoals": 1,
      "shPoints": 1,
      "shootingPct": 0.1375,
      "shootsCatches": "L",
      "shots": 80,
      "skaterFullName": "Dale Craigwell",
      "timeOnIcePerGame": null
    },
    {
      "assists": 15,
      "evGoals": 6,
      "evPoints": 20,
      "faceoffWinPct": null,
      "gameWinningGoals": 1,
      "gamesPlayed": 84,
      "goals": 7,
      "lastName": "Storm",
      "otGoals": 0,
      "penaltyMinutes": 44,
      "playerId": 8458589,
      "plusMinus": 5,
      "points": 22,
      "pointsPerGame": 0.2619,
      "positionCode": "L",
      "ppGoals": 1,
      "ppPoints": 2,
      "shGoals": 0,
      "shPoints": 0,
      "shootingPct": 0.07142,
      "shootsCatches": "L",
      "shots": 98,
      "skaterFullName": "Jim Storm",
      "timeOnIcePerGame": null
    },
    {
      "assists": 10,
      "evGoals": 8,
      "evPoints": 18,
      "faceoffWinPct": 0.33333,
      "gameWinningGoals": 1,
      "gamesPlayed": 106,
      "goals": 10,
      "lastName": "Sarault",
      "otGoals": 0,
      "penaltyMinutes": 51,
      "playerId": 8458575,
      "plusMinus": -20,
      "points": 20,
      "pointsPerGame": 0.18867,
      "positionCode": "L",
      "ppGoals": 2,
      "ppPoints": 2,
      "shGoals": 0,
      "shPoints": 0,
      "shootingPct": 0.07092,
      "shootsCatches": "L",
      "shots": 141,
      "skaterFullName": "Yves Sarault",
      "timeOnIcePerGame": null
    },
    {
      "assists": 10,
      "evGoals": 7,
      "evPoints": 17,
      "faceoffWinPct": 0,
      "gameWinningGoals": 0,
      "gamesPlayed": 106,
      "goals": 8,
      "lastName": "Wood",
      "otGoals": 0,
      "penaltyMinutes": 471,
      "playerId": 8458559,
      "plusMinus": -11,
      "points": 18,
      "pointsPerGame": 0.16981,
      "positionCode": "C",
      "ppGoals": 0,
      "ppPoints": 0,
      "shGoals": 1,
      "shPoints": 1,
      "shootingPct": 0.08421,
      "shootsCatches": "L",
      "shots": 95,
      "skaterFullName": "Dody Wood",
      "timeOnIcePerGame": null
    },
    {
      "assists": 12,
      "evGoals": 0,
      "evPoints": 8,
      "faceoffWinPct": 0.5,
      "gameWinningGoals": 0,
      "gamesPlayed": 113,
      "goals": 2,
      "lastName": "Brimanis",
      "otGoals": 0,
      "penaltyMinutes": 57,
      "playerId": 8458600,
      "plusMinus": -20,
      "points": 14,
      "pointsPerGame": 0.12389,
      "positionCode": "D",
      "ppGoals": 2,
      "ppPoints": 6,
      "shGoals": 0,
      "shPoints": 0,
      "shootingPct": 0.02,
      "shootsCatches": "R",
      "shots": 100,
      "skaterFullName": "Aris Brimanis",
      "timeOnIcePerGame": null
    },
    {
      "assists": 8,
      "evGoals": 3,
      "evPoints": 11,
      "faceoffWinPct": 0.55072,
      "gameWinningGoals": 0,
      "gamesPlayed": 52,
      "goals": 3,
      "lastName": "Nelson",
      "otGoals": 0,
      "penaltyMinutes": 20,
      "playerId": 8458550,
      "plusMinus": 0,
      "points": 11,
      "pointsPerGame": 0.21153,
      "positionCode": "C",
      "ppGoals": 0,
      "ppPoints": 0,
      "shGoals": 0,
      "shPoints": 0,
      "shootingPct": 0.0909,
      "shootsCatches": "L",
      "shots": 33,
      "skaterFullName": "Jeff Nelson",
      "timeOnIcePerGame": null
    },
    {
      "assists": 7,
      "evGoals": 0,
      "evPoints": 4,
      "faceoffWinPct": null,
      "gameWinningGoals": 0,
      "gamesPlayed": 34,
      "goals": 2,
      "lastName": "Snell",
      "otGoals": 0,
      "penaltyMinutes": 24,
      "playerId": 8458659,
      "plusMinus": -8,
      "points": 9,
      "pointsPerGame": 0.2647,
      "positionCode": "D",
      "ppGoals": 0,
      "ppPoints": 3,
      "shGoals": 2,
      "shPoints": 2,
      "shootingPct": 0.04081,
      "shootsCatches": "L",
      "shots": 49,
      "skaterFullName": "Chris Snell",
      "timeOnIcePerGame": null
    },
    {
      "assists": 9,
      "evGoals": 0,
      "evPoints": 7,
      "faceoffWinPct": null,
      "gameWinningGoals": 0,
      "gamesPlayed": 43,
      "goals": 0,
      "lastName": "Namestnikov",
      "otGoals": 0,
      "penaltyMinutes": 24,
      "playerId": 8458631,
      "plusMinus": -2,
      "points": 9,
      "pointsPerGame": 0.2093,
      "positionCode": "D",
      "ppGoals": 0,
      "ppPoints": 2,
      "shGoals": 0,
      "shPoints": 0,
      "shootingPct": 0,
      "shootsCatches": "R",
      "shots": 35,
      "skaterFullName": "Jevgeni Namestnikov",
      "timeOnIcePerGame": null
    },
    {
      "assists": 6,
      "evGoals": 1,
      "evPoints": 3,
      "faceoffWinPct": 1,
      "gameWinningGoals": 0,
      "gamesPlayed": 50,
      "goals": 2,
      "lastName": "Brennan",
      "otGoals": 0,
      "penaltyMinutes": 33,
      "playerId": 8458560,
      "plusMinus": -8,
      "points": 8,
      "pointsPerGame": 0.16,
      "positionCode": "D",
      "ppGoals": 1,
      "ppPoints": 5,
      "shGoals": 0,
      "shPoints": 0,
      "shootingPct": 0.02739,
      "shootsCatches": "R",
      "shots": 73,
      "skaterFullName": "Rich Brennan",
      "timeOnIcePerGame": null
    },
    {
      "assists": 4,
      "evGoals": 2,
      "evPoints": 4,
      "faceoffWinPct": null,
      "gameWinningGoals": 0,
      "gamesPlayed": 16,
      "goals": 3,
      "lastName": "Otevrel",
      "otGoals": 0,
      "penaltyMinutes": 2,
      "playerId": 8458647,
      "plusMinus": -11,
      "points": 7,
      "pointsPerGame": 0.4375,
      "positionCode": "C",
      "ppGoals": 1,
      "ppPoints": 3,
      "shGoals": 0,
      "shPoints": 0,
      "shootingPct": 0.2,
      "shootsCatches": "L",
      "shots": 15,
      "skaterFullName": "Jaroslav Otevrel",
      "timeOnIcePerGame": null
    },
    {
      "assists": 5,
      "evGoals": 2,
      "evPoints": 7,
      "faceoffWinPct": null,
      "gameWinningGoals": 0,
      "gamesPlayed": 107,
      "goals": 2,
      "lastName": "Stojanov",
      "otGoals": 0,
      "penaltyMinutes": 222,
      "playerId": 8458521,
      "plusMinus": -12,
      "points": 7,
      "pointsPerGame": 0.06542,
      "positionCode": "R",
      "ppGoals": 0,
      "ppPoints": 0,
      "shGoals": 0,
      "shPoints": 0,
      "shootingPct": 0.0625,
      "shootsCatches": "L",
      "shots": 32,
      "skaterFullName": "Alek Stojanov",
      "timeOnIcePerGame": null
    },
    {
      "assists": 5,
      "evGoals": 2,
      "evPoints": 6,
      "faceoffWinPct": null,
      "gameWinningGoals": 0,
      "gamesPlayed": 32,
      "goals": 2,
      "lastName": "Prochazka",
      "otGoals": 0,
      "penaltyMinutes": 8,
      "playerId": 8458649,
      "plusMinus": -2,
      "points": 7,
      "pointsPerGame": 0.21875,
      "positionCode": "R",
      "ppGoals": 0,
      "ppPoints": 1,
      "shGoals": 0,
      "shPoints": 0,
      "shootingPct": 0.04444,
      "shootsCatches": "R",
      "shots": 45,
      "skaterFullName": "Martin Prochazka",
      "timeOnIcePerGame": 755.0312
    },
    {
      "assists": 3,
      "evGoals": 3,
      "evPoints": 5,
      "faceoffWinPct": null,
      "gameWinningGoals": 0,
      "gamesPlayed": 68,
      "goals": 3,
      "lastName": "Patterson",
      "otGoals": 0,
      "penaltyMinutes": 56,
      "playerId": 8458662,
      "plusMinus": -10,
      "points": 6,
      "pointsPerGame": 0.08823,
      "positionCode": "R",
      "ppGoals": 0,
      "ppPoints": 0,
      "shGoals": 0,
      "shPoints": 1,
      "shootingPct": 0.08823,
      "shootsCatches": "R",
      "shots": 34,
      "skaterFullName": "Ed Patterson",
      "timeOnIcePerGame": null
    },
    {
      "assists": 2,
      "evGoals": 3,
      "evPoints": 5,
      "faceoffWinPct": null,
      "gameWinningGoals": 0,
      "gamesPlayed": 26,
      "goals": 3,
      "lastName": "Kaminsky",
      "otGoals": 0,
      "penaltyMinutes": 4,
      "playerId": 8458613,
      "plusMinus": 7,
      "points": 5,
      "pointsPerGame": 0.1923,
      "positionCode": "L",
      "ppGoals": 0,
      "ppPoints": 0,
      "shGoals": 0,
      "shPoints": 0,
      "shootingPct": 0.11111,
      "shootsCatches": "L",
      "shots": 27,
      "skaterFullName": "Yan Kaminsky",
      "timeOnIcePerGame": null
    },
    {
      "assists": 3,
      "evGoals": 2,
      "evPoints": 5,
      "faceoffWinPct": 0.38636,
      "gameWinningGoals": 0,
      "gamesPlayed": 34,
      "goals": 2,
      "lastName": "Fairchild",
      "otGoals": 0,
      "penaltyMinutes": 6,
      "playerId": 8458666,
      "plusMinus": -3,
      "points": 5,
      "pointsPerGame": 0.14705,
      "positionCode": "C",
      "ppGoals": 0,
      "ppPoints": 0,
      "shGoals": 0,
      "shPoints": 0,
      "shootingPct": 0.08,
      "shootsCatches": "L",
      "shots": 25,
      "skaterFullName": "Kelly Fairchild",
      "timeOnIcePerGame": null
    },
    {
      "assists": 4,
      "evGoals": 1,
      "evPoints": 4,
      "faceoffWinPct": null,
      "gameWinningGoals": 0,
      "gamesPlayed": 30,
      "goals": 1,
      "lastName": "Filimonov",
      "otGoals": 0,
      "penaltyMinutes": 18,
      "playerId": 8458563,
      "plusMinus": -10,
      "points": 5,
      "pointsPerGame": 0.16666,
      "positionCode": "D",
      "ppGoals": 0,
      "ppPoints": 0,
      "shGoals": 0,
      "shPoints": 1,
      "shootingPct": 0.06666,
      "shootsCatches": "R",
      "shots": 15,
      "skaterFullName": "Dmitri Filimonov",
      "timeOnIcePerGame": null
    },
    {
      "assists": 2,
      "evGoals": 2,
      "evPoints": 4,
      "faceoffWinPct": null,
      "gameWinningGoals": 0,
      "gamesPlayed": 25,
      "goals": 2,
      "lastName": "Fitzgerald",
      "otGoals": 0,
      "penaltyMinutes": 12,
      "playerId": 8458552,
      "plusMinus": 9,
      "points": 4,
      "pointsPerGame": 0.16,
      "positionCode": "C",
      "ppGoals": 0,
      "ppPoints": 0,
      "shGoals": 0,
      "shPoints": 0,
      "shootingPct": 0.1,
      "shootsCatches": "L",
      "shots": 20,
      "skaterFullName": "Rusty Fitzgerald",
      "timeOnIcePerGame": null
    },
    {
      "assists": 2,
      "evGoals": 2,
      "evPoints": 3,
      "faceoffWinPct": null,
      "gameWinningGoals": 0,
      "gamesPlayed": 17,
      "goals": 2,
      "lastName": "Leveque",
      "otGoals": 0,
      "penaltyMinutes": 21,
      "playerId": 8458556,
      "plusMinus": -3,
      "points": 4,
      "pointsPerGame": 0.23529,
      "positionCode": "C",
      "ppGoals": 0,
      "ppPoints": 1,
      "shGoals": 0,
      "shPoints": 0,
      "shootingPct": 0.13333,
      "shootsCatches": "R",
      "shots": 15,
      "skaterFullName": "Guy Leveque",
      "timeOnIcePerGame": null
    },
    {
      "assists": 4,
      "evGoals": 0,
      "evPoints": 4,
      "faceoffWinPct": 0.66666,
      "gameWinningGoals": 0,
      "gamesPlayed": 17,
      "goals": 0,
      "lastName": "Halverson",
      "otGoals": 0,
      "penaltyMinutes": 28,
      "playerId": 8458535,
      "plusMinus": -5,
      "points": 4,
      "pointsPerGame": 0.23529,
      "positionCode": "R",
      "ppGoals": 0,
      "ppPoints": 0,
      "shGoals": 0,
      "shPoints": 0,
      "shootingPct": 0,
      "shootsCatches": "L",
      "shots": 16,
      "skaterFullName": "Trevor Halverson",
      "timeOnIcePerGame": 716.5882
    },
    {
      "assists": 0,
      "evGoals": 2,
      "evPoints": 2,
      "faceoffWinPct": null,
      "gameWinningGoals": 1,
      "gamesPlayed": 35,
      "goals": 2,
      "lastName": "Dupre",
      "otGoals": 0,
      "penaltyMinutes": 16,
      "playerId": 8458564,
      "plusMinus": -7,
      "points": 2,
      "pointsPerGame": 0.05714,
      "positionCode": "L",
      "ppGoals": 0,
      "ppPoints": 0,
      "shGoals": 0,
      "shPoints": 0,
      "shootingPct": 0.06451,
      "shootsCatches": "L",
      "shots": 31,
      "skaterFullName": "Yanick Dupre",
      "timeOnIcePerGame": null
    },
    {
      "assists": 2,
      "evGoals": 0,
      "evPoints": 2,
      "faceoffWinPct": null,
      "gameWinningGoals": 0,
      "gamesPlayed": 7,
      "goals": 0,
      "lastName": "Kenady",
      "otGoals": 0,
      "penaltyMinutes": 0,
      "playerId": 8458686,
      "plusMinus": 0,
      "points": 2,
      "pointsPerGame": 0.28571,
      "positionCode": "R",
      "ppGoals": 0,
      "ppPoints": 0,
      "shGoals": 0,
      "shPoints": 0,
      "shootingPct": 0,
      "shootsCatches": "R",
      "shots": 4,
      "skaterFullName": "Chris Kenady",
      "timeOnIcePerGame": 513.7142
    },
    {
      "assists": 0,
      "evGoals": 1,
      "evPoints": 1,
      "faceoffWinPct": null,
      "gameWinningGoals": 0,
      "gamesPlayed": 12,
      "goals": 1,
      "lastName": "Redmond",
      "otGoals": 0,
      "penaltyMinutes": 20,
      "playerId": 8458593,
      "plusMinus": -3,
      "points": 1,
      "pointsPerGame": 0.08333,
      "positionCode": "L",
      "ppGoals": 0,
      "ppPoints": 0,
      "shGoals": 0,
      "shPoints": 0,
      "shootingPct": 0.11111,
      "shootsCatches": "L",
      "shots": 9,
      "skaterFullName": "Keith Redmond",
      "timeOnIcePerGame": null
    },
    {
      "assists": 0,
      "evGoals": 1,
      "evPoints": 1,
      "faceoffWinPct": null,
      "gameWinningGoals": 0,
      "gamesPlayed": 25,
      "goals": 1,
      "lastName": "Kudashov",
      "otGoals": 0,
      "penaltyMinutes": 4,
      "playerId": 8458616,
      "plusMinus": -3,
      "points": 1,
      "pointsPerGame": 0.04,
      "positionCode": "C",
      "ppGoals": 0,
      "ppPoints": 0,
      "shGoals": 0,
      "shPoints": 0,
      "shootingPct": 0.04166,
      "shootsCatches": "R",
      "shots": 24,
      "skaterFullName": "Alexei Kudashov",
      "timeOnIcePerGame": null
    },
    {
      "assists": 1,
      "evGoals": 0,
      "evPoints": 1,
      "faceoffWinPct": null,
      "gameWinningGoals": 0,
      "gamesPlayed": 8,
      "goals": 0,
      "lastName": "Groleau",
      "otGoals": 0,
      "penaltyMinutes": 6,
      "playerId": 8458555,
      "plusMinus": 3,
      "points": 1,
      "pointsPerGame": 0.125,
      "positionCode": "D",
      "ppGoals": 0,
      "ppPoints": 0,
      "shGoals": 0,
      "shPoints": 0,
      "shootingPct": 0,
      "shootsCatches": "L",
      "shots": 7,
      "skaterFullName": "Francois Groleau",
      "timeOnIcePerGame": null
    },
    {
      "assists": 1,
      "evGoals": 0,
      "evPoints": 1,
      "faceoffWinPct": null,
      "gameWinningGoals": 0,
      "gamesPlayed": 12,
      "goals": 0,
      "lastName": "Ambroziak",
      "otGoals": 0,
      "penaltyMinutes": 0,
      "playerId": 8458586,
      "plusMinus": -1,
      "points": 1,
      "pointsPerGame": 0.08333,
      "positionCode": "L",
      "ppGoals": 0,
      "ppPoints": 0,
      "shGoals": 0,
      "shPoints": 0,
      "shootingPct": 0,
      "shootsCatches": "L",
      "shots": 3,
      "skaterFullName": "Peter Ambroziak",
      "timeOnIcePerGame": null
    },
    {
      "assists": 1,
      "evGoals": 0,
      "evPoints": 1,
      "faceoffWinPct": null,
      "gameWinningGoals": 0,
      "gamesPlayed": 18,
      "goals": 0,
      "lastName": "Friedman",
      "otGoals": 0,
      "penaltyMinutes": 34,
      "playerId": 8458734,
      "plusMinus": 0,
      "points": 1,
      "pointsPerGame": 0.05555,
      "positionCode": "L",
      "ppGoals": 0,
      "ppPoints": 0,
      "shGoals": 0,
      "shPoints": 0,
      "shootingPct": 0,
      "shootsCatches": "L",
      "shots": 11,
      "skaterFullName": "Doug Friedman",
      "timeOnIcePerGame": 375.1111
    },
    {
      "assists": 0,
      "evGoals": 0,
      "evPoints": 0,
      "faceoffWinPct": null,
      "gameWinningGoals": 0,
      "gamesPlayed": 2,
      "goals": 0,
      "lastName": "Sundblad",
      "otGoals": 0,
      "penaltyMinutes": 0,
      "playerId": 8458533,
      "plusMinus": 0,
      "points": 0,
      "pointsPerGame": 0,
      "positionCode": "R",
      "ppGoals": 0,
      "ppPoints": 0,
      "shGoals": 0,
      "shPoints": 0,
      "shootingPct": 0,
      "shootsCatches": "R",
      "shots": 3,
      "skaterFullName": "Niklas Sundblad",
      "timeOnIcePerGame": null
    },
    {
      "assists": 0,
      "evGoals": 0,
      "evPoints": 0,
      "faceoffWinPct": null,
      "gameWinningGoals": 0,
      "gamesPlayed": 1,
      "goals": 0,
      "lastName": "Lavigne",
      "otGoals": 0,
      "penaltyMinutes": 0,
      "playerId": 8458539,
      "plusMinus": -1,
      "points": 0,
      "pointsPerGame": 0,
      "positionCode": "D",
      "ppGoals": 0,
      "ppPoints": 0,
      "shGoals": 0,
      "shPoints": 0,
      "shootingPct": null,
      "shootsCatches": "L",
      "shots": 0,
      "skaterFullName": "Eric Lavigne",
      "timeOnIcePerGame": null
    },
    {
      "assists": 0,
      "evGoals": 0,
      "evPoints": 0,
      "faceoffWinPct": null,
      "gameWinningGoals": 0,
      "gamesPlayed": 8,
      "goals": 0,
      "lastName": "Lindquist",
      "otGoals": 0,
      "penaltyMinutes": 2,
      "playerId": 8458569,
      "plusMinus": -2,
      "points": 0,
      "pointsPerGame": 0,
      "positionCode": "R",
      "ppGoals": 0,
      "ppPoints": 0,
      "shGoals": 0,
      "shPoints": 0,
      "shootingPct": 0,
      "shootsCatches": "L",
      "shots": 6,
      "skaterFullName": "Fredrik Lindquist",
      "timeOnIcePerGame": 738
    },
    {
      "assists": 0,
      "evGoals": 0,
      "evPoints": 0,
      "faceoffWinPct": null,
      "gameWinningGoals": 0,
      "gamesPlayed": 11,
      "goals": 0,
      "lastName": "Tiley",
      "otGoals": 0,
      "penaltyMinutes": 0,
      "playerId": 8458598,
      "plusMinus": -1,
      "points": 0,
      "pointsPerGame": 0,
      "positionCode": "D",
      "ppGoals": 0,
      "ppPoints": 0,
      "shGoals": 0,
      "shPoints": 0,
      "shootingPct": 0,
      "shootsCatches": "L",
      "shots": 2,
      "skaterFullName": "Brad Tiley",
      "timeOnIcePerGame": 708.7272
    },
    {
      "assists": 0,
      "evGoals": 0,
      "evPoints": 0,
      "faceoffWinPct": null,
      "gameWinningGoals": 0,
      "gamesPlayed": 3,
      "goals": 0,
      "lastName": "Boyer",
      "otGoals": 0,
      "penaltyMinutes": 0,
      "playerId": 8458602,
      "plusMinus": 0,
      "points": 0,
      "pointsPerGame": 0,
      "positionCode": "R",
      "ppGoals": 0,
      "ppPoints": 0,
      "shGoals": 0,
      "shPoints": 0,
      "shootingPct": 0,
      "shootsCatches": "R",
      "shots": 4,
      "skaterFullName": "Zac Boyer",
      "timeOnIcePerGame": null
    },
    {
      "assists": 0,
      "evGoals": 0,
      "evPoints": 0,
      "faceoffWinPct": null,
      "gameWinningGoals": 0,
      "gamesPlayed": 5,
      "goals": 0,
      "lastName": "Junker",
      "otGoals": 0,
      "penaltyMinutes": 0,
      "playerId": 8458606,
      "plusMinus": 0,
      "points": 0,
      "pointsPerGame": 0,
      "positionCode": "R",
      "ppGoals": 0,
      "ppPoints": 0,
      "shGoals": 0,
      "shPoints": 0,
      "shootingPct": 0,
      "shootsCatches": "L",
      "shots": 2,
      "skaterFullName": "Steve Junker",
      "timeOnIcePerGame": null
    },
    {
      "assists": 0,
      "evGoals": 0,
      "evPoints": 0,
      "faceoffWinPct": null,
      "gameWinningGoals": 0,
      "gamesPlayed": 11,
      "goals": 0,
      "lastName": "Morissette",
      "otGoals": 0,
      "penaltyMinutes": 57,
      "playerId": 8458660,
      "plusMinus": 1,
      "points": 0,
      "pointsPerGame": 0,
      "positionCode": "L",
      "ppGoals": 0,
      "ppPoints": 0,
      "shGoals": 0,
      "shPoints": 0,
      "shootingPct": 0,
      "shootsCatches": "L",
      "shots": 2,
      "skaterFullName": "Dave Morissette",
      "timeOnIcePerGame": 141.8181
    },
    {
      "assists": 0,
      "evGoals": 0,
      "evPoints": 0,
      "faceoffWinPct": null,
      "gameWinningGoals": 0,
      "gamesPlayed": 7,
      "goals": 0,
      "lastName": "Hollinger",
      "otGoals": 0,
      "penaltyMinutes": 2,
      "playerId": 8458667,
      "plusMinus": 0,
      "points": 0,
      "pointsPerGame": 0,
      "positionCode": "D",
      "ppGoals": 0,
      "ppPoints": 0,
      "shGoals": 0,
      "shPoints": 0,
      "shootingPct": 0,
      "shootsCatches": "L",
      "shots": 1,
      "skaterFullName": "Terry Hollinger",
      "timeOnIcePerGame": null
    },
    {
      "assists": 0,
      "evGoals": 0,
      "evPoints": 0,
      "faceoffWinPct": null,
      "gameWinningGoals": 0,
      "gamesPlayed": 4,
      "goals": 0,
      "lastName": "Struch",
      "otGoals": 0,
      "penaltyMinutes": 4,
      "playerId": 8458707,
      "plusMinus": -2,
      "points": 0,
      "pointsPerGame": 0,
      "positionCode": "C",
      "ppGoals": 0,
      "ppPoints": 0,
      "shGoals": 0,
      "shPoints": 0,
      "shootingPct": 0,
      "shootsCatches": "L",
      "shots": 3,
      "skaterFullName": "David Struch",
      "timeOnIcePerGame": null
    },
    {
      "assists": 0,
      "evGoals": 0,
      "evPoints": 0,
      "faceoffWinPct": null,
      "gameWinningGoals": 0,
      "gamesPlayed": 1,
      "goals": 0,
      "lastName": "Andrijevski",
      "otGoals": 0,
      "penaltyMinutes": 0,
      "playerId": 8458732,
      "plusMinus": 0,
      "points": 0,
      "pointsPerGame": 0,
      "positionCode": "R",
      "ppGoals": 0,
      "ppPoints": 0,
      "shGoals": 0,
      "shPoints": 0,
      "shootingPct": null,
      "shootsCatches": "R",
      "shots": 0,
      "skaterFullName": "Alexander Andrijevski",
      "timeOnIcePerGame": null
    },
    {
      "assists": 0,
      "evGoals": 0,
      "evPoints": 0,
      "faceoffWinPct": null,
      "gameWinningGoals": 0,
      "gamesPlayed": 3,
      "goals": 0,
      "lastName": "Jantunen",
      "otGoals": 0,
      "penaltyMinutes": 0,
      "playerId": 8458751,
      "plusMinus": -1,
      "points": 0,
      "pointsPerGame": 0,
      "positionCode": "C",
      "ppGoals": 0,
      "ppPoints": 0,
      "shGoals": 0,
      "shPoints": 0,
      "shootingPct": 0,
      "shootsCatches": "L",
      "shots": 7,
      "skaterFullName": "Marko Jantunen",
      "timeOnIcePerGame": null
    },
    {
      "assists": 0,
      "evGoals": 0,
      "evPoints": 0,
      "faceoffWinPct": null,
      "gameWinningGoals": 0,
      "gamesPlayed": 3,
      "goals": 0,
      "lastName": "Wiseman",
      "otGoals": 0,
      "penaltyMinutes": 0,
      "playerId": 8458796,
      "plusMinus": 0,
      "points": 0,
      "pointsPerGame": 0,
      "positionCode": "C",
      "ppGoals": 0,
      "ppPoints": 0,
      "shGoals": 0,
      "shPoints": 0,
      "shootingPct": 0,
      "shootsCatches": "L",
      "shots": 1,
      "skaterFullName": "Brian Wiseman",
      "timeOnIcePerGame": null
    },
    {
      "assists": 0,
      "evGoals": 0,
      "evPoints": 0,
      "faceoffWinPct": null,
      "gameWinningGoals": 0,
      "gamesPlayed": 3,
      "goals": 0,
      "lastName": "Gaul",
      "otGoals": 0,
      "penaltyMinutes": 4,
      "playerId": 8458801,
      "plusMinus": 0,
      "points": 0,
      "pointsPerGame": 0,
      "positionCode": "D",
      "ppGoals": 0,
      "ppPoints": 0,
      "shGoals": 0,
      "shPoints": 0,
      "shootingPct": 0,
      "shootsCatches": "R",
      "shots": 4,
      "skaterFullName": "Michael Gaul",
      "timeOnIcePerGame": 746.6666
    },
    {
      "assists": 0,
      "evGoals": 0,
      "evPoints": 0,
      "faceoffWinPct": null,
      "gameWinningGoals": 0,
      "gamesPlayed": 2,
      "goals": 0,
      "lastName": "Kravets",
      "otGoals": 0,
      "penaltyMinutes": 0,
      "playerId": 8458808,
      "plusMinus": -1,
      "points": 0,
      "pointsPerGame": 0,
      "positionCode": "L",
      "ppGoals": 0,
      "ppPoints": 0,
      "shGoals": 0,
      "shPoints": 0,
      "shootingPct": 0,
      "shootsCatches": "L",
      "shots": 2,
      "skaterFullName": "Mikhail Kravets",
      "timeOnIcePerGame": null
    }
  ],
  "total": 100
}
